josels/__init__.py
josels/cli.py
josels-0.1.3.dist-info/LICENSE.txt
josels-0.1.3.dist-info/METADATA
josels-0.1.3.dist-info/WHEEL
josels-0.1.3.dist-info/entry_points.txt
josels-0.1.3.dist-info/top_level.txt
josels-0.1.3.dist-info/RECORD
